[
    {
        "type": "message",
        "text": "再提出",
        "files": [
            {
                "id": "FN43EGFDG",
                "created": 1568826138,
                "timestamp": 1568826138,
                "name": "中間発表抄録1.docx",
                "title": "中間発表抄録1.docx",
                "mimetype": "application\/vnd.openxmlformats-officedocument.wordprocessingml.document",
                "filetype": "docx",
                "pretty_type": "Word Document",
                "user": "UHFLC6N4X",
                "editable": false,
                "size": 26942,
                "mode": "hosted",
                "is_external": false,
                "external_type": "",
                "is_public": true,
                "public_url_shared": false,
                "display_as_bot": false,
                "username": "",
                "url_private": "https:\/\/files.slack.com\/files-pri\/TGNPXK07J-FN43EGFDG\/__________________1.docx?t=xoxe-566813646256-1033738527330-1033738527506-fdbc90f512c5962200b2428b2867eaa5",
                "url_private_download": "https:\/\/files.slack.com\/files-pri\/TGNPXK07J-FN43EGFDG\/download\/__________________1.docx?t=xoxe-566813646256-1033738527330-1033738527506-fdbc90f512c5962200b2428b2867eaa5",
                "converted_pdf": "https:\/\/files.slack.com\/files-tmb\/TGNPXK07J-FN43EGFDG-b0d12deae0\/__________________1_converted.pdf?t=xoxe-566813646256-1033738527330-1033738527506-fdbc90f512c5962200b2428b2867eaa5",
                "thumb_pdf": "https:\/\/files.slack.com\/files-tmb\/TGNPXK07J-FN43EGFDG-b0d12deae0\/__________________1_thumb_pdf.png?t=xoxe-566813646256-1033738527330-1033738527506-fdbc90f512c5962200b2428b2867eaa5",
                "thumb_pdf_w": 909,
                "thumb_pdf_h": 1286,
                "permalink": "https:\/\/ohkawaralab.slack.com\/files\/UHFLC6N4X\/FN43EGFDG\/__________________1.docx",
                "permalink_public": "https:\/\/slack-files.com\/TGNPXK07J-FN43EGFDG-6c8e6d6b32",
                "is_starred": false,
                "has_rich_preview": false
            }
        ],
        "upload": true,
        "user": "UHFLC6N4X",
        "display_as_bot": false,
        "ts": "1568826139.000600",
        "client_msg_id": "b376cf60-5d47-4b57-b5d8-a3bdb283f4d6"
    },
    {
        "client_msg_id": "201b21e6-b210-4219-a23a-332b1ac7912c",
        "type": "message",
        "text": "登録してください",
        "user": "UHFLB6JPR",
        "ts": "1568846490.000300",
        "team": "TGNPXK07J",
        "user_team": "TGNPXK07J",
        "source_team": "TGNPXK07J",
        "user_profile": {
            "avatar_hash": "g73f794b1dc5",
            "image_72": "https:\/\/secure.gravatar.com\/avatar\/873f794b1dc5e80d3fd9893202850b31.jpg?s=72&d=https%3A%2F%2Fa.slack-edge.com%2Fdf10d%2Fimg%2Favatars%2Fava_0003-72.png",
            "first_name": "",
            "real_name": "大河原一憲",
            "display_name": "",
            "team": "TGNPXK07J",
            "name": "ohkawara_kazunori",
            "is_restricted": false,
            "is_ultra_restricted": false
        }
    },
    {
        "client_msg_id": "4fef6a4f-0166-4fa4-93dc-3a3a31371943",
        "type": "message",
        "text": "登録したら連絡をして",
        "user": "UHFLB6JPR",
        "ts": "1568846504.000600",
        "team": "TGNPXK07J",
        "user_team": "TGNPXK07J",
        "source_team": "TGNPXK07J",
        "user_profile": {
            "avatar_hash": "g73f794b1dc5",
            "image_72": "https:\/\/secure.gravatar.com\/avatar\/873f794b1dc5e80d3fd9893202850b31.jpg?s=72&d=https%3A%2F%2Fa.slack-edge.com%2Fdf10d%2Fimg%2Favatars%2Fava_0003-72.png",
            "first_name": "",
            "real_name": "大河原一憲",
            "display_name": "",
            "team": "TGNPXK07J",
            "name": "ohkawara_kazunori",
            "is_restricted": false,
            "is_ultra_restricted": false
        }
    },
    {
        "type": "message",
        "text": "提出済み発表会資料（PDF)",
        "files": [
            {
                "id": "FNKDXSXSB",
                "created": 1568873075,
                "timestamp": 1568873075,
                "name": "中間発表抄録.pdf",
                "title": "中間発表抄録.pdf",
                "mimetype": "application\/pdf",
                "filetype": "pdf",
                "pretty_type": "PDF",
                "user": "UHFLC6N4X",
                "editable": false,
                "size": 221561,
                "mode": "hosted",
                "is_external": false,
                "external_type": "",
                "is_public": true,
                "public_url_shared": false,
                "display_as_bot": false,
                "username": "",
                "url_private": "https:\/\/files.slack.com\/files-pri\/TGNPXK07J-FNKDXSXSB\/__________________.pdf?t=xoxe-566813646256-1033738527330-1033738527506-fdbc90f512c5962200b2428b2867eaa5",
                "url_private_download": "https:\/\/files.slack.com\/files-pri\/TGNPXK07J-FNKDXSXSB\/download\/__________________.pdf?t=xoxe-566813646256-1033738527330-1033738527506-fdbc90f512c5962200b2428b2867eaa5",
                "thumb_pdf": "https:\/\/files.slack.com\/files-tmb\/TGNPXK07J-FNKDXSXSB-6b3f490858\/___________________thumb_pdf.png?t=xoxe-566813646256-1033738527330-1033738527506-fdbc90f512c5962200b2428b2867eaa5",
                "thumb_pdf_w": 910,
                "thumb_pdf_h": 1286,
                "permalink": "https:\/\/ohkawaralab.slack.com\/files\/UHFLC6N4X\/FNKDXSXSB\/__________________.pdf",
                "permalink_public": "https:\/\/slack-files.com\/TGNPXK07J-FNKDXSXSB-8a6a42577d",
                "is_starred": false,
                "has_rich_preview": false
            }
        ],
        "upload": true,
        "user": "UHFLC6N4X",
        "display_as_bot": false,
        "ts": "1568873076.000100",
        "client_msg_id": "cc747d4f-74eb-4380-bdc8-89c8c77804d6"
    }
]